LICENSE.rst
MANIFEST.in
README.md
setup.py
docs/files/foyer_citation.bib
examples/ethane.py
foyer/__init__.py
foyer/atomtyper.py
foyer/element.py
foyer/exceptions.py
foyer/forcefield.py
foyer/smarts.py
foyer/smarts_graph.py
foyer/validator.py
foyer/version.py
foyer/xml_writer.py
foyer.egg-info/PKG-INFO
foyer.egg-info/SOURCES.txt
foyer.egg-info/dependency_links.txt
foyer.egg-info/entry_points.txt
foyer.egg-info/not-zip-safe
foyer.egg-info/top_level.txt
foyer/examples/files/opls-silica.xml
foyer/examples/files/oplsaa_alkane.xml
foyer/examples/files/oplsaa_with_silica.xml
foyer/examples/files/output.xml
foyer/forcefields/__init__.py
foyer/forcefields/ff.xsd
foyer/forcefields/forcefields.py
foyer/forcefields/xml/oplsaa.xml
foyer/forcefields/xml/trappe-ua.xml
foyer/opls_validation/1-bromobutane/1-bromobutane.gro
foyer/opls_validation/1-bromobutane/1-bromobutane.top
foyer/opls_validation/1-bromopropane/1-bromopropane.gro
foyer/opls_validation/1-bromopropane/1-bromopropane.top
foyer/opls_validation/1-butanethiol/1-butanethiol.gro
foyer/opls_validation/1-butanethiol/1-butanethiol.top
foyer/opls_validation/1-butanol/1-butanol.gro
foyer/opls_validation/1-butanol/1-butanol.top
foyer/opls_validation/1-chlorobutane/1-chlorobutane.gro
foyer/opls_validation/1-chlorobutane/1-chlorobutane.top
foyer/opls_validation/1-chloronaphthalene/1-chloronaphthalene.gro
foyer/opls_validation/1-chloronaphthalene/1-chloronaphthalene.top
foyer/opls_validation/1-cyclopropylpropane/1-cyclopropylpropane.gro
foyer/opls_validation/1-cyclopropylpropane/1-cyclopropylpropane.top
foyer/opls_validation/1-ethylpropylamine/1-ethylpropylamine.gro
foyer/opls_validation/1-ethylpropylamine/1-ethylpropylamine.top
foyer/opls_validation/1-nitropropane/1-nitropropane.gro
foyer/opls_validation/1-nitropropane/1-nitropropane.top
foyer/opls_validation/1-octanol/1-octanol.gro
foyer/opls_validation/1-octanol/1-octanol.top
foyer/opls_validation/1-pentanol/1-pentanol.gro
foyer/opls_validation/1-pentanol/1-pentanol.top
foyer/opls_validation/11-dichloroethane/11-dichloroethane.gro
foyer/opls_validation/11-dichloroethane/11-dichloroethane.top
