Metadata-Version: 1.1
Name: foyer
Version: 0.7.6
Summary: Foyer: Atomtyping and forcefield applying. 
Home-page: https://github.com/mosdef-hub/foyer
Author: Janos Sallai, Christoph Klein
Author-email: janos.sallai@vanderbilt.edu, christoph.klein@vanderbilt.edu
License: MIT
Download-URL: https://github.com/mosdef-hub/foyer/tarball/0.7.6
Keywords: foyer
Platform: UNKNOWN
Classifier: Development Status :: 4 - Beta
Classifier: Intended Audience :: Science/Research
Classifier: Intended Audience :: Developers
Classifier: License :: OSI Approved :: MIT License
Classifier: Natural Language :: English
Classifier: Programming Language :: Python
Classifier: Programming Language :: Python :: 2.7
Classifier: Programming Language :: Python :: 3
Classifier: Topic :: Scientific/Engineering :: Chemistry
Classifier: Operating System :: Microsoft :: Windows
Classifier: Operating System :: POSIX
Classifier: Operating System :: Unix
Classifier: Operating System :: MacOS
